"venue, journal.S.HTML"
venue.S.HTML
vegan/___license/license.s.HTML
vegan/___license/list/gpl-3.0-standalone.html
vegan/___license/list/non-commercial.S.HTML
vegan/___license/list/vegan.s.HTML
vegan/___objectives/book/Vitamin B.S.HTML
vegan/___objectives/book/Vitamin K.S.HTML
vegan/___objectives/objectives - elliptic.S.HTML
vegan/___objectives/objectives.S.HTML
vegan/__dictionary/vegan_1
vegan/__init__.py
vegan/__status/API/DB/records.json
vegan/__status/API/status.proc.py
vegan/__status/main/.gitignore
vegan/__status/main/DB/records.json
vegan/__status/main/output.json
vegan/__status/main/status.proc.py
vegan/_essence/__init__.py
vegan/_essence/activate_alert/__init__.py
vegan/_essence/activate_alert/parse_exception.py
vegan/_essence/essence.S.HTML
vegan/_essence/merge/__init__.py
vegan/_essence/scan/__init__.py
vegan/_essence/seek/__init__.py
vegan/_ops/clique/__init__.py
vegan/adventures/_ops/_clique.py
vegan/adventures/_ops/monitor.py
vegan/adventures/_ops/off.py
vegan/adventures/_ops/on.py
vegan/adventures/_ops/refresh.py
vegan/adventures/_ops/status.py
vegan/adventures/adventures.S.HTML
vegan/adventures/alerting/__init__.py
vegan/adventures/alerting/parse_exception.py
vegan/adventures/customs/__init__.py
vegan/adventures/customs/_ops/off.py
vegan/adventures/customs/_ops/on.py
vegan/adventures/customs/_ops/status.py
vegan/adventures/customs/clique.py
vegan/adventures/customs/configs_school/embargo.NFT
vegan/adventures/customs/customs.S.HTML
vegan/adventures/monetary/.gitignore
vegan/adventures/monetary/DB/vegan_tract/.gitignore
vegan/adventures/monetary/DB/vegan_tract/__itinerary/itinerary.S.HTML
vegan/adventures/monetary/DB/vegan_tract/_land/_land.S.HTML
vegan/adventures/monetary/DB/vegan_tract/_land/find_name.py
vegan/adventures/monetary/DB/vegan_tract/_land/insert_document.py
vegan/adventures/monetary/DB/vegan_tract/_land/retrieve_every.py
vegan/adventures/monetary/DB/vegan_tract/cautionary_ingredients/cautionary_ingredients.S.HTML
vegan-2.1.5.dist-info/METADATA
vegan-2.1.5.dist-info/WHEEL
vegan-2.1.5.dist-info/entry_points.txt
vegan-2.1.5.dist-info/RECORD
